<?xml version="1.0" encoding="utf-8" ?>
<dwsync>
<file name="1.eml" server="profiles.artistforce.com//var/www/vhosts/everient.com/httpdocs/" local="129486126310292729" remote="129486126230000000" />
<file name="10.eml" server="profiles.artistforce.com//var/www/vhosts/everient.com/httpdocs/" local="129484872423231232" remote="129484906240000000" />
<file name="11.eml" server="profiles.artistforce.com//var/www/vhosts/everient.com/httpdocs/" local="129484872957721803" remote="129484906240000000" />
<file name="12.eml" server="profiles.artistforce.com//var/www/vhosts/everient.com/httpdocs/" local="129484872948201258" remote="129484906250000000" />
<file name="13.eml" server="profiles.artistforce.com//var/www/vhosts/everient.com/httpdocs/" local="129484872946501161" remote="129484906250000000" />
<file name="14.eml" server="profiles.artistforce.com//var/www/vhosts/everient.com/httpdocs/" local="129484872936630597" remote="129484906260000000" />
<file name="15.eml" server="profiles.artistforce.com//var/www/vhosts/everient.com/httpdocs/" local="129484872932260347" remote="129484906260000000" />
<file name="16.eml" server="profiles.artistforce.com//var/www/vhosts/everient.com/httpdocs/" local="129484872923319835" remote="129484906270000000" />
<file name="17.eml" server="profiles.artistforce.com//var/www/vhosts/everient.com/httpdocs/" local="129484872921599737" remote="129484906280000000" />
<file name="18.eml" server="profiles.artistforce.com//var/www/vhosts/everient.com/httpdocs/" local="129484872912939241" remote="129484906280000000" />
<file name="19.eml" server="profiles.artistforce.com//var/www/vhosts/everient.com/httpdocs/" local="129484872911689170" remote="129484906290000000" />
<file name="2.eml" server="profiles.artistforce.com//var/www/vhosts/everient.com/httpdocs/" local="129484872902918668" remote="129484906290000000" />
<file name="20.eml" server="profiles.artistforce.com//var/www/vhosts/everient.com/httpdocs/" local="129484872901238572" remote="129484906300000000" />
<file name="21.eml" server="profiles.artistforce.com//var/www/vhosts/everient.com/httpdocs/" local="129484872900208513" remote="129484906310000000" />
<file name="22.eml" server="profiles.artistforce.com//var/www/vhosts/everient.com/httpdocs/" local="129484872891318005" remote="129484906310000000" />
<file name="23.eml" server="profiles.artistforce.com//var/www/vhosts/everient.com/httpdocs/" local="129484872889427897" remote="129484906320000000" />
<file name="24.eml" server="profiles.artistforce.com//var/www/vhosts/everient.com/httpdocs/" local="129484872880957412" remote="129484906330000000" />
<file name="25.eml" server="profiles.artistforce.com//var/www/vhosts/everient.com/httpdocs/" local="129484872878947297" remote="129484906330000000" />
<file name="26.eml" server="profiles.artistforce.com//var/www/vhosts/everient.com/httpdocs/" local="129484872869676767" remote="129484906340000000" />
<file name="27.eml" server="profiles.artistforce.com//var/www/vhosts/everient.com/httpdocs/" local="129484872867546645" remote="129484906340000000" />
<file name="28.eml" server="profiles.artistforce.com//var/www/vhosts/everient.com/httpdocs/" local="129484872858886150" remote="129484906350000000" />
<file name="29.eml" server="profiles.artistforce.com//var/www/vhosts/everient.com/httpdocs/" local="129484872847195481" remote="129484906360000000" />
<file name="3.eml" server="profiles.artistforce.com//var/www/vhosts/everient.com/httpdocs/" local="129484872845655393" remote="129484906360000000" />
<file name="30.eml" server="profiles.artistforce.com//var/www/vhosts/everient.com/httpdocs/" local="129484872844695338" remote="129484906370000000" />
<file name="31.eml" server="profiles.artistforce.com//var/www/vhosts/everient.com/httpdocs/" local="129484872835834831" remote="129484906380000000" />
<file name="32.eml" server="profiles.artistforce.com//var/www/vhosts/everient.com/httpdocs/" local="129484872833384691" remote="129484906390000000" />
<file name="33.eml" server="profiles.artistforce.com//var/www/vhosts/everient.com/httpdocs/" local="129484872824754198" remote="129484906400000000" />
<file name="34.eml" server="profiles.artistforce.com//var/www/vhosts/everient.com/httpdocs/" local="129484872813393548" remote="129484906410000000" />
<file name="35.eml" server="profiles.artistforce.com//var/www/vhosts/everient.com/httpdocs/" local="129484872811403434" remote="129484906420000000" />
<file name="36.eml" server="profiles.artistforce.com//var/www/vhosts/everient.com/httpdocs/" local="129484872802442921" remote="129484906430000000" />
<file name="37.eml" server="profiles.artistforce.com//var/www/vhosts/everient.com/httpdocs/" local="129484872800652819" remote="129484906440000000" />
<file name="38.eml" server="profiles.artistforce.com//var/www/vhosts/everient.com/httpdocs/" local="129484872791872317" remote="129484906450000000" />
<file name="39.eml" server="profiles.artistforce.com//var/www/vhosts/everient.com/httpdocs/" local="129484872779471608" remote="129484906460000000" />
<file name="4.eml" server="profiles.artistforce.com//var/www/vhosts/everient.com/httpdocs/" local="129484872762500637" remote="129484906470000000" />
<file name="40.eml" server="profiles.artistforce.com//var/www/vhosts/everient.com/httpdocs/" local="129484872749659902" remote="129484906480000000" />
<file name="41.eml" server="profiles.artistforce.com//var/www/vhosts/everient.com/httpdocs/" local="129484872732008893" remote="129484906490000000" />
<file name="42.eml" server="profiles.artistforce.com//var/www/vhosts/everient.com/httpdocs/" local="129484872715437945" remote="129484906500000000" />
<file name="43.eml" server="profiles.artistforce.com//var/www/vhosts/everient.com/httpdocs/" local="129484872702727218" remote="129484906500000000" />
<file name="44.eml" server="profiles.artistforce.com//var/www/vhosts/everient.com/httpdocs/" local="129484872691586581" remote="129484906530000000" />
<file name="45.eml" server="profiles.artistforce.com//var/www/vhosts/everient.com/httpdocs/" local="129484872673785563" remote="129484906540000000" />
<file name="46.eml" server="profiles.artistforce.com//var/www/vhosts/everient.com/httpdocs/" local="129484872654314449" remote="129484906540000000" />
<file name="47.eml" server="profiles.artistforce.com//var/www/vhosts/everient.com/httpdocs/" local="129484872644133867" remote="129484906560000000" />
<file name="48.eml" server="profiles.artistforce.com//var/www/vhosts/everient.com/httpdocs/" local="129484872642493773" remote="129484906570000000" />
<file name="49.eml" server="profiles.artistforce.com//var/www/vhosts/everient.com/httpdocs/" local="129484872632813219" remote="129484906580000000" />
<file name="5.1.1.eml" server="profiles.artistforce.com//var/www/vhosts/everient.com/httpdocs/" local="129484872631263130" remote="129484906580000000" />
<file name="5.eml" server="profiles.artistforce.com//var/www/vhosts/everient.com/httpdocs/" local="129484872621352564" remote="129484906590000000" />
<file name="50.eml" server="profiles.artistforce.com//var/www/vhosts/everient.com/httpdocs/" local="129484872611011972" remote="129484906600000000" />
<file name="51.eml" server="profiles.artistforce.com//var/www/vhosts/everient.com/httpdocs/" local="129484872600831390" remote="129484906610000000" />
<file name="52.eml" server="profiles.artistforce.com//var/www/vhosts/everient.com/httpdocs/" local="129484872590600805" remote="129484906630000000" />
<file name="53.eml" server="profiles.artistforce.com//var/www/vhosts/everient.com/httpdocs/" local="129484872589090718" remote="129484906630000000" />
<file name="54.eml" server="profiles.artistforce.com//var/www/vhosts/everient.com/httpdocs/" local="129484872579160150" remote="129484906640000000" />
<file name="55.eml" server="profiles.artistforce.com//var/www/vhosts/everient.com/httpdocs/" local="129484872569269585" remote="129484906650000000" />
<file name="56.eml" server="profiles.artistforce.com//var/www/vhosts/everient.com/httpdocs/" local="129484872567489483" remote="129484906660000000" />
<file name="57.eml" server="profiles.artistforce.com//var/www/vhosts/everient.com/httpdocs/" local="129484872557988939" remote="129484906660000000" />
<file name="58.eml" server="profiles.artistforce.com//var/www/vhosts/everient.com/httpdocs/" local="129484872556428850" remote="129484906670000000" />
<file name="59.eml" server="profiles.artistforce.com//var/www/vhosts/everient.com/httpdocs/" local="129484872546728295" remote="129484906680000000" />
<file name="6.eml" server="profiles.artistforce.com//var/www/vhosts/everient.com/httpdocs/" local="129484872544788184" remote="129484906680000000" />
<file name="60.eml" server="profiles.artistforce.com//var/www/vhosts/everient.com/httpdocs/" local="129484872535147633" remote="129484906690000000" />
<file name="7.eml" server="profiles.artistforce.com//var/www/vhosts/everient.com/httpdocs/" local="129484872525107059" remote="129484906700000000" />
<file name="8.eml" server="profiles.artistforce.com//var/www/vhosts/everient.com/httpdocs/" local="129484872523636975" remote="129484906700000000" />
<file name="9.eml" server="profiles.artistforce.com//var/www/vhosts/everient.com/httpdocs/" local="129484872513076371" remote="129484906710000000" />
<file name="arf1.txt" server="profiles.artistforce.com//var/www/vhosts/everient.com/httpdocs/" local="129484872414810750" remote="129484906720000000" />
<file name="arf2.txt" server="profiles.artistforce.com//var/www/vhosts/everient.com/httpdocs/" local="129484872414950758" remote="129484906720000000" />
<file name="arf3.txt" server="profiles.artistforce.com//var/www/vhosts/everient.com/httpdocs/" local="129484872415120768" remote="129484906730000000" />
<file name="arf4.txt" server="profiles.artistforce.com//var/www/vhosts/everient.com/httpdocs/" local="129484872415540792" remote="129484906740000000" />
<file name="arf5.txt" server="profiles.artistforce.com//var/www/vhosts/everient.com/httpdocs/" local="129484872415800807" remote="129484906740000000" />
<file name="arf6.txt" server="profiles.artistforce.com//var/www/vhosts/everient.com/httpdocs/" local="129484872415980817" remote="129484906750000000" />
<file name="exchange1.eml" server="profiles.artistforce.com//var/www/vhosts/everient.com/httpdocs/" local="129484872492195176" remote="129484906760000000" />
<file name="exchange2.eml" server="profiles.artistforce.com//var/www/vhosts/everient.com/httpdocs/" local="129484872474594170" remote="129484906760000000" />
<file name="exchange3.eml" server="profiles.artistforce.com//var/www/vhosts/everient.com/httpdocs/" local="129484872464153572" remote="129484906770000000" />
<file name="fbl-aol.txt" server="profiles.artistforce.com//var/www/vhosts/everient.com/httpdocs/" local="129484872416970874" remote="129484906770000000" />
<file name="fbl-comcast.txt" server="profiles.artistforce.com//var/www/vhosts/everient.com/httpdocs/" local="129484872417160885" remote="129484906780000000" />
<file name="fbl-hotmail.txt" server="profiles.artistforce.com//var/www/vhosts/everient.com/httpdocs/" local="129484872417330894" remote="129484906780000000" />
<file name="fbl-yahoo.txt" server="profiles.artistforce.com//var/www/vhosts/everient.com/httpdocs/" local="129484872418030934" remote="129484906790000000" />
<file name="hotmailbounce.txt" server="profiles.artistforce.com//var/www/vhosts/everient.com/httpdocs/" local="129484872418290949" remote="129484906800000000" />
<file name="testfile.eml" server="profiles.artistforce.com//var/www/vhosts/everient.com/httpdocs/" local="129484872452842925" remote="129484906800000000" />
<file name="unsubscribe.txt" server="profiles.artistforce.com//var/www/vhosts/everient.com/httpdocs/" local="129484872418930986" remote="129484906810000000" />
<file name="xe-test.txt" server="profiles.artistforce.com//var/www/vhosts/everient.com/httpdocs/" local="129484916561605802" remote="129484916530000000" />
</dwsync>